{
  "com.badlogic.gdx.graphics.g2d.BitmapFont": {
    "default-font": {
      "file": "default.fnt"
    }
  },
  "com.badlogic.gdx.scenes.scene2d.ui.Label$LabelStyle": {
    "default": {
      "font": "default-font",
      "fontColor": "white"
    }
  },
  "com.badlogic.gdx.scenes.scene2d.ui.TextButton$TextButtonStyle": {
    "default": {
      "font": "default-font",
      "fontColor": "white",
      "downFontColor": "red",
      "up": "default-round",
      "down": "default-round-down",
      "checked": "default-round"
    }
  },
  "com.badlogic.gdx.scenes.scene2d.ui.ScrollPane$ScrollPaneStyle": {
    "default": {
      "vScroll": "default-scroll",
      "hScrollKnob": "default-round-large"
    }
  },
  "com.badlogic.gdx.scenes.scene2d.ui.Window$WindowStyle": {
    "default": {
      "titleFont": "default-font",
      "background": "default-window",
      "titleFontColor": "white"
    }
  },
  "com.badlogic.gdx.scenes.scene2d.ui.SelectBox$SelectBoxStyle": {
    "default": {
      "font": "default-font",
      "fontColor": "white",
      "background": "default-select",
      "scrollStyle": "default",
      "listStyle": "default"
    }
  },
  "com.badlogic.gdx.scenes.scene2d.ui.List$ListStyle": {
    "default": {
      "font": "default-font",
      "selection": "default-select-selection"
    }
  },
  "com.badlogic.gdx.scenes.scene2d.ui.Slider$SliderStyle": {
    "default": {
      "background": "default-slider",
      "knob": "default-slider-knob"
    }
  },
  "com.badlogic.gdx.scenes.scene2d.ui.TextField$TextFieldStyle": {
    "default": {
      "font": "default-font",
      "fontColor": "white",
      "background": "default-textfield",
      "cursor": "default-cursor",
      "selection": "default-selection"
    }
  },
  "com.badlogic.gdx.scenes.scene2d.ui.CheckBox$CheckBoxStyle": {
    "default": {
      "font": "default-font",
      "checkboxOn": "default-checkbox-on",
      "checkboxOff": "default-checkbox-off"
    }
  }
}